adafruit_circuitpython_imageload-1.24.5.dist-info/licenses/LICENSE
adafruit_imageload/__init__.py
adafruit_imageload/displayio_types.py
adafruit_imageload/gif.py
adafruit_imageload/jpg.py
adafruit_imageload/png.py
adafruit_imageload/tilegrid_inflator.py
adafruit_imageload/bmp/__init__.py
adafruit_imageload/bmp/indexed.py
adafruit_imageload/bmp/negative_height_check.py
adafruit_imageload/bmp/truecolor.py
adafruit_imageload/pnm/__init__.py
adafruit_imageload/pnm/pbm_ascii.py
adafruit_imageload/pnm/pbm_binary.py
adafruit_imageload/pnm/ppm_ascii.py
adafruit_imageload/pnm/ppm_binary.py
adafruit_imageload/pnm/pgm/__init__.py
adafruit_imageload/pnm/pgm/ascii.py
adafruit_imageload/pnm/pgm/binary.py
adafruit_circuitpython_imageload-1.24.5.dist-info/METADATA
adafruit_circuitpython_imageload-1.24.5.dist-info/WHEEL
adafruit_circuitpython_imageload-1.24.5.dist-info/top_level.txt
adafruit_circuitpython_imageload-1.24.5.dist-info/RECORD
